fastanalysis/__init__.py
fastanalysis/load.py
fastanalysis/plot.py
fastanalysis-0.0.3.dist-info/LICENSE
fastanalysis-0.0.3.dist-info/METADATA
fastanalysis-0.0.3.dist-info/WHEEL
fastanalysis-0.0.3.dist-info/top_level.txt
fastanalysis-0.0.3.dist-info/RECORD
